voici/__init__.py
voici/_version.py
voici-0.10.0.dist-info/METADATA
voici-0.10.0.dist-info/WHEEL
voici-0.10.0.dist-info/licenses/LICENSE
voici-0.10.0.dist-info/RECORD
