Metadata-Version: 2.4
Name: voici
Version: 0.10.0
Summary: Voici turns Jupyter notebooks into static web applications
Project-URL: Homepage, https://github.com/voila-dashboards/voici
Author: Voila Development Team
License: BSD License
License-File: LICENSE
Keywords: Emscripten,Jupyter,JupyterLite,Voici,Voila
Classifier: Framework :: Jupyter
Classifier: License :: OSI Approved :: BSD License
Classifier: Programming Language :: Python
Classifier: Programming Language :: Python :: 3
Classifier: Programming Language :: Python :: 3.10
Classifier: Programming Language :: Python :: 3.11
Classifier: Programming Language :: Python :: 3.12
Classifier: Programming Language :: Python :: 3.13
Classifier: Programming Language :: Python :: 3.14
Requires-Python: >=3.10
Requires-Dist: jupyterlite-xeus>=4.3.6
Requires-Dist: voici-core
Provides-Extra: dev
Requires-Dist: hatch; extra == 'dev'
Requires-Dist: ruff<0.12,>=0.11; extra == 'dev'
Provides-Extra: docs
Requires-Dist: myst-parser; extra == 'docs'
Requires-Dist: pydata-sphinx-theme; extra == 'docs'
Requires-Dist: sphinx; extra == 'docs'
Requires-Dist: sphinx-autobuild; extra == 'docs'
Requires-Dist: sphinxcontrib-video; extra == 'docs'
